LICENSE
MANIFEST.in
README.md
package.json
setup.py
dash_grid/DashGrid.py
dash_grid/__init__.py
dash_grid/_imports_.py
dash_grid/dash_grid.min.js
dash_grid/dash_grid.min.js.map
dash_grid/metadata.json
dash_grid/package-info.json
dash_grid.egg-info/PKG-INFO
dash_grid.egg-info/SOURCES.txt
dash_grid.egg-info/dependency_links.txt
dash_grid.egg-info/top_level.txt