Metadata-Version: 1.1
Name: dash-grid
Version: 0.0.8
Summary: the grid of the dash 
Home-page: UNKNOWN
Author: kalimuthu periyasamy <1995kalimuthu@gmail.com>
Author-email: UNKNOWN
License: MIT
Platform: UNKNOWN
Classifier: Framework :: Dash
